# 方法调用

## 源码

```java
public class Demo1 {
    private void test1(){}
    private final void test2(){}
    public void test3(){}
    public static void test4(){}
    public static void main(String[] args) {
        Demo1 demo = new Demo1();
        demo.test1();
        demo.test2();
        demo.test3();
        demo.test4();
        Demo1.test4();
    }
}
```

## 反编译字节码

```java
  public static void main(java.lang.String[]);
    descriptor: ([Ljava/lang/String;)V
    flags: ACC_PUBLIC, ACC_STATIC
    Code:
      stack=2, locals=2, args_size=1
         0: new           #2                  // class bytecode/Demo1
         3: dup
         4: invokespecial #3                  // Method "<init>":()V
         7: astore_1
         8: aload_1
         9: invokespecial #4                  // Method test1:()V
        12: aload_1
        13: invokespecial #5                  // Method test2:()V
        16: aload_1
        17: invokevirtual #6                  // Method test3:()V
        20: aload_1
        21: pop
        22: invokestatic  #7                  // Method test4:()V
        25: invokestatic  #7                  // Method test4:()V
        28: return
      LocalVariableTable:
        Start  Length  Slot  Name   Signature
            0      24     0  args   [Ljava/lang/String;
            8      16     1  demo   Lbytecode/Demo1;
```

### new      #2

创建【对象】，给对象分配堆内存，执行成功会将【对象引用】压入操作数栈

### dup

赋值操作数栈栈顶的内容，本例即为【对象引用】

为什么需要两份引用呢？一个是要配合 `invokespecial` 调用该对象的构造方法 `"<init>":()V` （会消耗掉栈顶一个引用），另一个要配合 `astore_1` 赋值给局部变量

### invokespecial   #3

执行类本身的构造方法

执行完后，对象引用会弹出操作数栈，此时操作数栈顶还剩一个对象引用

### astore_1

将操作数栈顶的引用弹出，存入局部变量表1号槽位

>new  #2、dup、invokespecial  #3、astore_1
>
>以上指令对应源码：Demo1 demo = new Demo1();

---

### aload_1

### invokespecial   #4

### aload_1

### invokespecial   #5 

### aload_1

### invokevirtual   #6 

>以上字节码指令对应源码：
>
>demo.test1();
>demo.test2();
>demo.test3();
>
>都是先将对象引用压入操作数栈，然后在调用对象的方法，最后对象引用弹出操作数栈

---

下面的字节码比较有意思

### aload_1

将对象引用压入操作数栈

### pop

把对象引用从操作数栈弹出

### invokestatic  #7

执行`test4`静态方法

调用了两次`test4`静态方法

### return

方法结束

## 思考

为什么将对象引入压入操作数栈，然后又弹出呢？

说明执行 `invokestatic` 这条指令根本就不需要依赖引用 `demo`这个数据。从而说名了静态方法的调用依赖的是类对象。源码中虽然使用了对象实例调用静态方法，但从字节码来看，其实这是一种浪费，造成了一次不不必要的压栈与弹栈。

## 总结

* 最终方法（final），私有方法（private），构造方法都是由 `invokespecial` 指令来调用，属于静态绑定
* 普通成员方法是由 `invokevirtual` 调用，属于动态绑定，即支持多态
* 成员方法与静态方法调用的另一个区别是，执行方法前是否需要【对象引用】
* 还有一个执行 `invokespecial` 的情况是通过 super 调用父类方法