#     构造方法

构造方法如果细分，可以分为两类，一类是`<cinit>()V`，一类是`<init>()V`

## \<cinit\>()V

### 源码

```java
public class Demo11 {
    static int i = 10;
    static {
        i = 20;
    }
    static {
        i = 30;
    }
    public static void main(String[] args) {
        System.out.println(i); // 结果为 30
    }
}
```

### 反编译字节码

```java
static {};
    descriptor: ()V
    flags: ACC_STATIC
    Code:
      stack=1, locals=0, args_size=0
         0: bipush        10
         2: putstatic     #3                  // Field i:I
         5: bipush        20
         7: putstatic     #3                  // Field i:I
        10: bipush        30
        12: putstatic     #3                  // Field i:I
        15: return
```

编译器会按从上至下的顺序，收集所有 static 静态代码块和静态成员赋值的代码，合并为一个特殊的方
法 <cinit>()V

<cinit>()V 方法会在类加载的初始化阶段被调用

#### bipush    10

将10压入操作数栈

#### putstatic  #3

将10赋值给常量池3号位置int类型的变量i

以上两个指令对应源码：`static int i = 10`

#### bipush    20

将20压入操作数栈

#### putstatic  #3

将20赋值给常量池3号位置int类型的变量i

以上两个指令对应源码：

```java
static {
    i = 20;
}
```

#### bipush    30

将30压入操作数栈

#### putstatic  #3

将30赋值给常量池3号位置int类型的变量i

```java
static {
     i = 30;
}
```

综上得知，最后输出结果为30

## \<init\>()V

编译器会按从上至下的顺序，收集所有 {} 代码块和成员变量赋值的代码，形成新的构造方法，但原始构
造方法内的代码总是在最后

### 源码

```java
public class Demo12 {
    private String a = "s1";
    {
        b = 20;
    }
    private int b = 10;
    {
        a = "s2";
    }

    public Demo12(String a, int b) {
        this.a = a;
        this.b = b;
    }

    public static void main(String[] args) {
        Demo12 demo = new Demo12("s3", 30);
        System.out.println(demo.a);
        System.out.println(demo.b);
    }
}
```

## 反编译字节码

```java
public bytecode.Demo12(java.lang.String, int);
    descriptor: (Ljava/lang/String;I)V
    flags: ACC_PUBLIC
    Code:
      stack=2, locals=3, args_size=3
            0: aload_0
            1: invokespecial #1 	 // super.<init>()V
            4: aload_0
            5: ldc #2 				// <- "s1"
            7: putfield #3 			// -> this.a
            10: aload_0
            11: bipush 20 			// <- 20
            13: putfield #4 		// -> this.b
            16: aload_0
            17: bipush 10 			// <- 10
            19: putfield #4 		// -> this.b
            22: aload_0
            23: ldc #5 				// <- "s2"
            25: putfield #3 		// -> this.a
            28: aload_0 			// ------------------------------
            29: aload_1 			// <- slot 1(a) "s3"  |
            30: putfield #3 		// -> this.a 		  |
            33: aload_0 			//					 |
            34: iload_2 			// <- slot 2(b) 30    |
            35: putfield #4 		// -> this.b --------------------
		   38: return
   LocalVariableTable:
        Start  Length  Slot  Name   Signature
            0      39     0  this   Lbytecode/Demo12;
            0      39     1     a   Ljava/lang/String;
            0      39     2     b   I
```

#### aload_0

将局部变量表0号槽位的数据压入操作数栈

也就是将this引用压入操作数栈

#### invokespecial #1     

调用了父类（Object）的`init`构造方法

#### aload_0

将this压入操作数栈

#### ldc      #2

将运行常量池2号位置的数据（s1）压入操作数栈

#### putfield      #3

将s1赋值给常量池3号位置String类型的变量a

>aload_0、ldc   #2、putfield    #3
>
>以上三个指令的作用：将s1赋值给this成员变量a
>
>对应源码：private String a = "s1";

#### aload_0

将this压入操作数栈

#### bipush     10

将10压入操作数栈

#### putfield     #4

将10赋值给常量池4号位置int类型的变量b

>aload_0、bipush  10、putfield    #4
>
>以上三个指令的作用：将10赋值给this成员变量b
>
>对应源码：{b = 10;}

16~25行分析方式类型，不再赘述，从28开始分析

#### 28: aload_0

将this压入操作数栈

#### aload_1

将a压入操作数栈

#### putfield    #3

将a的引用赋值给常量池3号位置String类型的变量a

>aload_0、aload_1、putfield   #3
>
>以上三个指令的作用：将a赋值给this成员变量a
>
>对应源码：this.a = a;

#### aload_0

将this压入操作数栈

#### iload_2

将b压入操作数栈

#### putfield    #4

将b的引用赋值给常量池4号位置int类型的变量b

>aload_0、iload_2、putfield   #4
>
>以上三个指令的作用：将b赋值给this成员变量b
>
>对应源码：this.b= b;

#### return

构造方法执行结束