# 语法糖

## 编译期处理

所谓的 **语法糖** ，其实就是指`java`编译器把`*.java`源码编译为`*.class`字节码的过程中，自动生成和转换的一些代码。这样就给程序员减轻了一些负担，算是`java`编译器给的福利。

注意，以下代码的分析，借助了 javap 工具，idea 的反编译功能，idea 插件 jclasslib 等工具。另外，编译器转换的结果直接就是 class 字节码，只是为了便于阅读，给出了 **几乎等价** 的 java 源码方式，并不是编译器还会转换出中间的 java 源码，切记。

## 默认构造器

### 源码

```java
package sugar;
public class Candy1 {
}
```

### 编译成`class`后的代码

```java
package sugar;
public class Candy1 {
    public Candy1() {
        super();	// 即调用父类 Object 的无参构造方法，即调用 java/lang/Object."<init>":()V
    }
}
```

源码中并没有无参构造，但编译后的class中，会存在无参构造函数，并且构造函数中调用了父类的无参构造，这些操作都是编译器自动为做的，但编译器为我们做这些的前提是我们在源码中不定义无参构造。

## 自动拆装箱

### 代码1

```java
package sugar;

/**
 * @author : mfh
 * @date : 2020-01-20 10:23
 **/
public class Candy2 {
    public static void main(String[] args) {
        Integer x = 1;
        int y = x;
    }
}
```

这段代码在 JDK 5 之前是无法编译通过的，必须改写为下面的

### 代码2

```java
package sugar;

/**
 * @author : mfh
 * @date : 2020-01-20 10:23
 **/
public class Candy2 {
    public static void main(String[] args) {
        Integer x = Integer.valueOf(1);
        int y = x.intValue();
    }
}
```

显然之前版本的代码太麻烦了，需要在基本类型和包装类型之间来回转换（尤其是集合类中操作的都是包装类型），因此这些转换的事情在 JDK 5 以后都由编译器在编译阶段完成。即 **代码1** 都会在编译阶段被转换为 **代码2**。

## 泛型集合和取值

泛型也是在 JDK 5 开始加入的特性，但 java 在编译泛型代码后会执行 **泛型擦除** 的动作，即泛型信息在编译为字节码之后就丢失了，实际的类型都当做了 Object 类型来处理。

### 源码

```java
package sugar;

import java.util.ArrayList;
import java.util.List;

/**
 * @author : mfh
 * @date : 2020-01-20 10:31
 **/
public class Candy3 {
    public static void main(String[] args) {
        List<Integer> list = new ArrayList<Integer>();
        list.add(10);               // 实际调用的是 list.add(Object e)
        Integer x = list.get(0);    // Object o = list.get(int index)
    }
}
```

在取值时，编译器真正生成的字节码中，还要额外做一个类型转换的操作：

```java
//	需要将 Object 转为 Integer
Integer x = (Integer)list.get(0);
```

如果前面的 x 变量类型修改为 int 基本类型那么最终生成的字节码是：

```java
//	需要将 Object 转为 Integer, 并执行拆箱操作 
int x = ((Integer)list.get(0)).intValue();
```

还好这些操作都不用程序员完成，编译器都替我们做了。

### 部分反编译后的字节码

```java
public static void main(java.lang.String[]);
    descriptor: ([Ljava/lang/String;)V
    flags: ACC_PUBLIC, ACC_STATIC
    Code:
      stack=2, locals=3, args_size=1
         0: new           #2                  // class java/util/ArrayList
         3: dup
         4: invokespecial #3                  // Method java/util/ArrayList."<init>":()V
         7: astore_1
         8: aload_1
         9: bipush        10
        11: invokestatic  #4                  // Method java/lang/Integer.valueOf:(I)Ljava/lang/Integer;
        14: invokeinterface #5,  2            // InterfaceMethod java/util/List.add:(Ljava/lang/Object;)Z
        19: pop
        20: aload_1
        21: iconst_0
        22: invokeinterface #6,  2            // InterfaceMethod java/util/List.get:(I)Ljava/lang/Object;
        27: checkcast     #7                  // class java/lang/Integer
        30: astore_2
        31: return
      LineNumberTable:
        line 12: 0
        line 13: 8
        line 14: 20
        line 15: 31
      LocalVariableTable:
        Start  Length  Slot  Name   Signature
            0      32     0  args   [Ljava/lang/String;
            8      24     1  list   Ljava/util/List;
           31       1     2     x   Ljava/lang/Integer;
      LocalVariableTypeTable:
        Start  Length  Slot  Name   Signature
            8      24     1  list   Ljava/util/List<Ljava/lang/Integer;>;
```

类似的字节码分析在前面的文章中已有详细分析，这里只是简要分析

> ​		 0: new                  #2                  // class java/util/ArrayList
> ​         3: dup
> ​         4: invokespecial   #3                  // Method java/util/ArrayList."<init>":()V
> ​         7: astore_1
>
> 以上字节码对应的源码：List<Integer> list = new ArrayList<Integer>();

#### aload_1

加载局部变量表1号槽位的数据到操作数栈，即`list`对象引用

#### bipush    10

将10压入操作数栈，为了执行后面的`list.add(10)`

#### invokestatic  #4  

执行静态方法 `Method java/lang/Integer.valueOf`

为什么要将int做包装呢？因为`list.add(Object o)`的参数类型为Object，所以要将int变成包装类型

#### invokeinterface #5,  2

接口方法调用，支持多台

调用了`java/util/List.add:(Ljava/lang/Object;)Z`方法，由此可以看出什么叫泛型擦除，也就是编译成字节码以后，执行的代码其实已经不区分集合中是`String`还是`Integer`了,统一当成`Object`类型，泛型信息在此就丢掉了。

#### aload_1

加载局部变量表1号槽位的数据到操作数栈，即`list`对象引用

#### iconst_0

将`0`压入操作数栈，为了后面执行`list.get(0)`

#### invokeinterface #6,  2

调用接口方法 `java/util/List.get:(I)Ljava/lang/Object`

从集合中取出的值的类型是`Object`，并不是`Integer`，这也是泛型擦除。

#### checkcast     #7

强制类型转换，将`Object`强制转换成`Integer`

#### astore_2

将转换完的`Integer`类型的数值存入`slot 2`

泛型擦除，擦除的是方法体（Code：.....）的泛型信息。从上面的字节码中可以看到`LocalVariableTypeTable`仍然保留了方法参数泛型的信息

### LocalVariableTypeTable

包含方法参数的类型信息

由以下字节码得知`main`方法中，`list`局部变量的泛型信息

```java
LocalVariableTypeTable:
        Start  Length  Slot  Name   Signature
            8      24     1  list   Ljava/util/List<Ljava/lang/Integer;>;
```

`list`是局部变量，它的泛型信息我们只能在字节码中看到，并不能通过反射得到，只有在方法的参数和返回值上使用的泛型的泛型信息，才能通过反射得到。

使用反射，仍然能够获得这些信息：

```java
public class Candy3 {
    public Set<Integer> test(List<String> list, Map<Integer, Object> map) {
        return null;
    }
}
```

获取`test`方法的参数泛型信息

```java
public class Client {
    public static void main(String[] args) throws NoSuchMethodException {
        final Method test = Candy3.class.getMethod("test", List.class, Map.class);
        final Type[] types = test.getGenericParameterTypes();
        for (Type type : types) {
            // 检查是否为参数化类型，即带有泛型类型，因为有可能是原始类型而不是泛型类型
            if (type instanceof ParameterizedType) {
                ParameterizedType parameterizedType = (ParameterizedType) type;
                final Type rawType = parameterizedType.getRawType();
                System.out.println("原始类型 - " + rawType);
                final Type[] actualTypeArguments = parameterizedType.getActualTypeArguments();
                for (int i = 0; i < actualTypeArguments.length; i++) {
                    System.out.printf("泛型参数[%d] - %s\n", i, actualTypeArguments[i]);
                }
            }
        }
    }
}
// 原始类型 - interface java.util.List
// 泛型参数[0] - class java.lang.String
// 原始类型 - interface java.util.Map
// 泛型参数[0] - class java.lang.Integer
// 泛型参数[1] - class java.lang.Object
```

## 可变参数

可变参数也是 `JDK 5` 开始加入的新特性

### 源码

```java
public class Candy4 {
    public static void test(String ...str) {
        String[] arr = str;
        System.out.println(arr);
    }

    public static void main(String[] args) {
        test("hello", "java");
    }
}
```

可变参数 `String... args`其实是一个 `String[] args`，从代码中的赋值语句中就可以看出来。 同样`java`编译器会在编译期间将上述代码变换为：

```java
public class Candy4 {
    public static void test(String ...str) {
        String[] arr = str;     // 直接赋值
        System.out.println(arr);
    }

    public static void main(String[] args) {
        test(new String[]{"hello", "java"});
    }
}
```

注意 如果调用了 foo() 则等价代码为 foo(new String[]{}) ，创建了一个空的数组，而不会传递 null 进去。

## foreach 循环

仍是`JDK 5`开始引入的语法糖，数组的循环。

### 源码

```java
public class Candy5_1 {
    public static void main(String[] args) {
        int[] array = {1, 2, 3, 4, 5}; // 数组赋初值的简化写法也是语法糖哦
        for (int e : array) {
            System.out.println(e);
        }
    }
}
```

会被编译器转换为：

```java
public class Candy5_1 {
    public Candy5_1() {
    }
    public static void main(String[] args) {
        int[] array = new int[]{1, 2, 3, 4, 5};
        for (int i = 0; i < array.length; ++i) {
            int e = array[i];
            System.out.println(e);
        }
    }
}
```

而集合的循环：

```java
public class Candy5_2 {
    public static void main(String[] args) {
        List<Integer> list = Arrays.asList(1,2,3,4,5);
        for (Integer i : list) {
            System.out.println(i);
        }
    }
}
```

实际被编译器转换为对迭代器的调用：

```java
public class Candy5_2 {
    public Candy5_2() {
    }

    public static void main(String[] args) {
        List<Integer> list = Arrays.asList(1, 2, 3, 4, 5);
        Iterator iter = list.iterator();
        while (iter.hasNext()) {
            Integer e = (Integer) iter.next();
            System.out.println(e);
        }
    }
}
```

注意：`foreach`循环写法，能够配合数组，以及所有实现了`Iterable`接口的集合类一起使用，其中`Iterable`用来获取集合的迭代器（ Iterator ）

## switch 字符串

从`JDK 7`开始，switch 可以作用于字符串和枚举类，这个功能其实也是语法糖。

原生的`switch`字节码指令中，并不支持字符串和枚举类，语法糖是通过一些转换，从而使用现有的语法实现了switch对字符串和枚举类的支持。

### 源码

```java
public class Candy6_1 {
    public static void choose(String str) {
        switch (str) {
            case "hello": {
                System.out.println("h");
                break;
            }
            case "world": {
                System.out.println("w");
                break;
            }
        }
    }
}
```

注意：`switch`配合`String`和枚举使用时，变量不能为`null`，原因分析完语法糖转换后的代码应当自然清楚。

### 编译后的类

```java
public class Candy6_1 {
    public Candy6_1() {}
    
    public static void choose(String str) {
        byte var2 = -1;
        switch(str.hashCode()) {
        case 99162322:
            if (str.equals("hello")) {
                var2 = 0;
            }
            break;
        case 113318802:
            if (str.equals("world")) {
                var2 = 1;
            }
        }

        switch(var2) {
        case 0:
            System.out.println("h");
            break;
        case 1:
            System.out.println("w");
        }
    }
}
```

可以看到，编译成字节码后，将一个`switch`拆分成了两个`switch`。两个字符串常量的`hashcode`可以在编译期确定，第一个`switch`比较目标字符串（参数）的哈希码与`hello`或`world`的哈希码是否相等，如果匹配到了，还要进一步判断，目标字符串是否与`hello`或者`world`相等（`equals`），如果相等会定义一个临时变量`var`，如果与`hello`匹配，则`var`赋值为0，如果与`world`匹配，则`var`赋值为1，如果都不匹配则`var`等于-1。

经过第一个`switch`后，第二个`switch`来进一步匹配`byte`的值，如果0则打印`h`；如果1则打印`w`；如果-1就什么都不打印。

执行了两遍`switch`，第一遍是根据字符串的`hashCode`和`equals`将字符串的转换为相应`byte`类型，第二遍才是利用`byte`执行进行比较。

 为什么第一遍时必须既比较`hashCode`，又利用`equals`比较呢？如果刚一开始就使用`equals`逐一进行比较，效率会很低，`hashCode`是为了提高效率，减少可能的比较，因为绝大字符串的哈希码是唯一的，使用`hashcode`能够较快的定位到目标字符串上。

既然使用了哈希码比较，为什么内部还要使用equals再次比较呢？

绝大字符串的哈希码是唯一的，但是也有相同的，使用`equals`是为了防止`hashCode`冲突。

例如`BM`和`C.`这两个字符串的`hashCode`值都是`2123` 。只通过哈希码进行比较，是区分不出来目标字符是`BM`还是`C.`

```java
public class Candy6_2 {
    public static void choose(String str) {
        switch (str) {
            case "BM": {
                System.out.println("h");
                break;
            }
            case "C.": {
                System.out.println("w");
                break;
            }
        }
    }
}
```

会被编译器转换为：

```java
public class Candy6_2 {
    public Candy6_2() {
    }

    public static void choose(String str) {
        byte x = -1;
        switch (str.hashCode()) {
            // hashCode 值可能相同，需要进一步用 equals 比较
            case 2123:
                if (str.equals("C.")) {
                    x = 1;
                } else if (str.equals("BM")) {
                    x = 0;
                }
            default:
                switch (x) {
                    case 0:
                        System.out.println("h");
                        break;
                    case 1:
                        System.out.println("w");
                }
        }
    }
}
```

结论：比较时不能光使用`hashcode`，还要使用`equals`来确保相同。

## switch 枚举

### 源码

```java
enum Sex {
    MALE, FEMALE
}

public class Candy7 {
    public static void foo(Sex sex) {
        switch (sex) {
            case MALE:
                System.out.println("男");
                break;
            case FEMALE:
                System.out.println("女");
                break;
        }
    }
}
```

### 编译后的类

```java
public class Candy7 {
    /**
     * 定义一个合成类（仅 jvm 使用，对我们不可见）
     * <p>
     * 用来映射枚举的 ordinal 与数组元素的关系
     * <p>
     * 枚举的 ordinal 表示枚举对象的序号，从 0 开始
     * <p>
     * 即 MALE 的 ordinal()=0，FEMALE 的 ordinal()=1
     */

    // 字节码中类不是这个名字
    static class $MAP {
        // 数组大小即为枚举元素个数，里面存储case用来对比的数字 static int[] map = new int[2];
        // 数组长度2就是根据枚举元素个数得到的
        static {
            map[Sex.MALE.ordinal()] = 1;
            map[Sex.FEMALE.ordinal()] = 2;
        }
    }

    public static void foo(Sex sex) {
        int x = $MAP.map[sex.ordinal()];
        switch (x) {
            case 1:
                System.out.println("男");
                break;
            case 2:
                System.out.println("女");
                break;
        }
    }
}
```

1. 生成合成类
2. 初始化静态数组，数组长度视枚举元素个数而定
3. 执行静态代码块，根据枚举元素的`ordinal`方法，初始化数组值，`MALE`的`ordinal`等于0；`FEMALE`的`ordinal`等于1，所以数组0位置的数值为1，数组1位置的数值为2。
4. 将目标枚举的`ordinal`作为传入数组，获取数组中值
5. 将此值再做`switch`判断，如果匹配1则打印男，如果匹配2则打印女

## 枚举类

`JDK 7`新增了枚举类

### 源码

```java
enum Sex {
    MALE,FEMALE
}
```

### 编译后的代码

```java
public final class Sex extends Enum<Sex> {

    public static final Sex MALE;
    public static final Sex FEMALE;
    private static final Sex[] $VALUES;
   
    static {
        MALE = new Sex("MALE", 0);
        FEMALE = new Sex("FEMALE", 1);
        $VALUES = new Sex[]{MALE, FEMALE};
    }

    /**
     * Sole constructor.  Programmers cannot invoke this constructor.
     * <p>
     * It is for use by code emitted by the compiler in response to
     * <p>
     * enum type declarations.
     *
     * @param name-   The name of this enum constant, which is the identifier
     *                <p>
     *                used to declare it.
     * @param ordinal - The ordinal of this enumeration constant (its position
     *                <p>
     *                in the enum declaration, where the initial constant is
     *                <p>
     *                assigned
     */

    // 构造方法为私有，使用者不能创建实例对象
    private Sex(String name, int ordinal) {
        super(name, ordinal);
    }

    public static Sex[] values() {
        return $VALUES.clone();
    }

    public static Sex valueOf(String name) {
        return Enum.valueOf(Sex.class, name);
    }
}
```

枚举类的本质也是一个类（`Class`）

枚举类与普通类的区别是什么呢？普通类的实例对象可以有无穷多个，因为你可以用`new`关键字创建对象，而枚举类的实例个数是有限的，此例子中，枚举类只有两个实例对象。

由反编译后等价的`java`源码得知，`Sex`枚举类是`final`的，因此得知枚举类不能被继承。它本身继承`Enum`类，此类支持泛型。

## try-with-resources

`JDK 7`**开始新增了对需要关闭的资源处理的特殊语法**`try-with-resources`

```java
try(资源变量 = 创建资源对象){
} catch( ) {
    
}
```

其中资源对象需要实现`AutoCloseable`接口，例如`InputStream 、 OutputStream 、Connection 、 Statement 、 ResultSet`等接口都实现了`AutoCloseable` ，使用`try-with-resources`可以不用写`finally`语句块，编译器会帮助生成关闭资源代码。

### 源码

```java
public class Candy9 {

    public static void main(String[] args) {
        try(InputStream is = new FileInputStream("d:\\1.txt")) {
            System.out.println(is);
        } catch (IOException e) {
            e.printStackTrace();
        }
    }
}
```



### 编译后的代码

```java
import java.io.FileInputStream;
import java.io.IOException;
import java.io.InputStream;

public class Candy9 {
    public Candy9() {
    }

    public static void main(String[] args) {
        try {
            InputStream is = new FileInputStream("d:\\1.txt");
            Throwable var2 = null;

            try {
                System.out.println(is);
            } catch (Throwable var12) {
                // var12 是代码中出现的异常
                var2 = var12;
                throw var12;
            } finally {
                // 判断资源不为空
                if (is != null) {
                    if (var2 != null) {
                        try {
                            is.close();
                        } catch (Throwable var11) {
                            // 如果 close 出现异常，作为被压制异常添加 
                            var2.addSuppressed(var11);
                        }
                    } else {
                        //	如果我们代码没有异常，close 出现的异常就是最后 catch 块中的 e
                        is.close();
                    }
                }

            }
        } catch (IOException var14) {
            var14.printStackTrace();
        }

    }
}
```

为什么要设计一个 `addSuppressed(Throwable e)` （添加被压制异常）的方法呢？是为了防止异常信息的丢失（想想`try-with-resources`生成的`fianlly`中如果抛出了异常）：

```java
public class Test6 {
   public static void main(String[] args) {
        try (MyResource resource = new MyResource()) {
            int i = 1 / 0;
        } catch (Exception e) {
            e.printStackTrace();
        }
    }
}

class MyResource implements AutoCloseable {
    public void close() throws Exception {
        throw new Exception("close 异常");
    }
}
```

输出：

```java
java.lang.ArithmeticException: / by zero
at test.Test6.main(Test6.java:7)
Suppressed: java.lang.Exception: close 异常
at test.MyResource.close(Test6.java:18)
at test.Test6.main(Test6.java:6)

```

如以上代码所示，两个异常信息都不会丢。

## 方法重写时的桥接方法

方法重写时的返回值分两种情况：

1. 父子类返回值完全一致
2. 子类返回值是父类返回值的子类

### 源码

```java
public class A {
    public Number m() {
        return 1;
    }
}
```

```java
public class B extends A {
    // 子类返回值 Integer 是父类返回值 Number 的子类
    @Override
    public Integer m() {
        return 2;
    }
}
```

为什么子类可以有这样的重写方式呢？

对于子类，`java`编译器会做如下处理

### 反编译后的部分字节码

```java
public sugar.bridge.B();
    descriptor: ()V
    flags: ACC_PUBLIC
    Code:
      stack=1, locals=1, args_size=1
         0: aload_0
         1: invokespecial #1                  // Method sugar/bridge/A."<init>":()V
         4: return
      LineNumberTable:
        line 7: 0
      LocalVariableTable:
        Start  Length  Slot  Name   Signature
            0       5     0  this   Lsugar/bridge/B;

  public java.lang.Integer m();
    descriptor: ()Ljava/lang/Integer;
    flags: ACC_PUBLIC
    Code:
      stack=1, locals=1, args_size=1
         0: iconst_2
         1: invokestatic  #2                  // Method java/lang/Integer.valueOf:(I)Ljava/lang/Integer;
         4: areturn
      LineNumberTable:
        line 10: 0
      LocalVariableTable:
        Start  Length  Slot  Name   Signature
            0       5     0  this   Lsugar/bridge/B;

  public java.lang.Number m();
    descriptor: ()Ljava/lang/Number;
    flags: ACC_PUBLIC, ACC_BRIDGE, ACC_SYNTHETIC
    Code:
      stack=1, locals=1, args_size=1
         0: aload_0
         1: invokevirtual #3                  // Method m:()Ljava/lang/Integer;
         4: areturn
      LineNumberTable:
        line 7: 0
      LocalVariableTable:
        Start  Length  Slot  Name   Signature
            0       5     0  this   Lsugar/bridge/B;
```

### 编译后的类

```java
class B extends A {
	public Integer m() {
        return 2;
    }
	// 此方法才是真正重写了父类 public Number m() 方法 
    // 仅对虚拟机可见
    public synthetic bridge Number m() {
	//	调用 public Integer m()
        return m();
    }
}
```

其中桥接（`bridge`）方法比较特殊，仅对`java`虚拟机可见，并且与原来的`public Integer m()`没有命名冲突。

解释了为什么子类可以有这样的重写方式呢？`public synthetic bridge Number m()`才是真正的方法重写，它内部调用了我们自己定义的`public Integer m()`。

### 反射验证

```java
public class Client {
    public static void main(String[] args) {
        final Method[] declaredMethods = B.class.getDeclaredMethods();
        for (Method declaredMethod : declaredMethods) {
            System.out.println(declaredMethod);
        }
    }
}
```

输出结果：

```java
public java.lang.Integer sugar.bridge.B.m()
public java.lang.Number sugar.bridge.B.m()
```

一个是自己写的方法；一个是自动生成的桥接方法。

## 匿名内部类

### 源码

```java
public class Candy11 {
    public static void main(String[] args) {
        Runnable runnable = new Runnable() {

            @Override
            public void run() {
                System.out.println("ok");
            }
        };
    }
}
```

### 编译后的类

```java
// 额外生成的类
final class Candy11$1 implements Runnable {
	Candy11$1() {}
	public void run() {
		System.out.println("ok");
    }
}

public class Candy11 {
	public static void main(String[] args) {
		Runnable runnable = new Candy11$1();
	}
}

```

匿名内部类会生成一个额外的类。

## 引用局部变量的匿名内部类

### 源码

```java
public class Candy11 {
    public static void test(final int x) {
        Runnable runnable = new Runnable() {
            @Override
            public void run() {
                System.out.println("ok:" + x);
            }
        };
    }
}
```

内部类`run`方法内部使用到了局部变量`x`。

### 编译后的类

```java

//	额外生成的类
final class Candy11$1 implements Runnable {
	int val$x;
	Candy11$1(int x) {
		this.val$x = x;
    }
    public void run() {
        System.out.println("ok:" + this.val$x);
    }
}
```

```java
public class Candy11 {
	public static void test(final int x) {
		Runnable runnable = new Candy11$1(x);
	}
}
```

注意：这同时解释了为什么匿名内部类引用局部变量时，局部变量必须是 final 的：因为在创建`Candy11$1`对象时，将 x 的值赋值给了`Candy11$1`对象的`vale$x`属性， 所以`x`不应该在发生变化了，如果变化（不是`final`的），那么`val$x`属性没有机会跟着一起变化，就会造成数据不一致。